{"1UxBLSbN": {"passed_count_linkFile": "0", "itogBoolValue": "False", "trueElems": {}, "passed_count_currentFile": "0", "isPassedCheck": "False"}, "Ab7BwRWJ": {"passed_count_linkFile": "0", "itogBoolValue": "False", "trueElems": {}, "passed_count_currentFile": "0", "isPassedCheck": "False"}, "ziPm5MRZ": {"passed_count_linkFile": "1", "itogBoolValue": "True", "trueElems": {"05-01-\u041a\u0413-07_\u041a\u0416_\u04213_R24.\u0424\u0425": ["3486542"]}, "passed_count_currentFile": "0", "isPassedCheck": "False"}, "UqxB6S1H": {"passed_count_linkFile": "0", "itogBoolValue": "False", "trueElems": {}, "passed_count_currentFile": "0", "isPassedCheck": "False"}, "C5UZwUE5": {"passed_count_linkFile": "0", "itogBoolValue": "False", "trueElems": {}, "passed_count_currentFile": "0", "isPassedCheck": "False"}, "hXs6E9ua": {"passed_count_linkFile": "0", "itogBoolValue": "False", "trueElems": {}, "passed_count_currentFile": "0", "isPassedCheck": "False"}, "b4qk3lbG": {"passed_count_linkFile": "0", "itogBoolValue": "False", "trueElems": {}, "passed_count_currentFile": "0", "isPassedCheck": "False"}, "kphhLjlv": {"passed_count_linkFile": "0", "itogBoolValue": "False", "trueElems": {}, "passed_count_currentFile": "0", "isPassedCheck": "False"}, "MQ03W3mo": {"passed_count_linkFile": "1", "itogBoolValue": "True", "trueElems": {"05-01-\u041a\u0413-07_\u041a\u0416_\u04213_R24.\u0424\u0425": ["3557466"]}, "passed_count_currentFile": "0", "isPassedCheck": "False"}, "wmoGqCYD": {"passed_count_linkFile": "0", "itogBoolValue": "False", "trueElems": {}, "passed_count_currentFile": "0", "isPassedCheck": "False"}, "JvbnxU03": {"passed_count_linkFile": "0", "itogBoolValue": "False", "trueElems": {}, "passed_count_currentFile": "0", "isPassedCheck": "False"}, "UAB1UOXE": {"passed_count_linkFile": "0", "itogBoolValue": "False", "trueElems": {}, "passed_count_currentFile": "0", "isPassedCheck": "False"}, "qDunX4CJ": {"passed_count_linkFile": "0", "itogBoolValue": "False", "trueElems": {}, "passed_count_currentFile": "0", "isPassedCheck": "False"}, "kJUhFvC2": {"passed_count_linkFile": "0", "itogBoolValue": "False", "trueElems": {}, "passed_count_currentFile": "0", "isPassedCheck": "False"}, "PE8ABPkX": {"passed_count_linkFile": "0", "itogBoolValue": "False", "trueElems": {}, "passed_count_currentFile": "0", "isPassedCheck": "False"}, "dq6HsrVq": {"passed_count_linkFile": "0", "itogBoolValue": "True", "trueElems": {"05-01-\u041a\u0413-07_\u0410\u0420_\u041a\u0420_\u041f\u0430\u0440\u043a\u0438\u043d\u0433+\u04213_R24.\u0424\u0425": ["32544956", "32545159", "32545310", "32545400", "32545607", "32545680", "32545772", "32572746", "32572922", "32573366", "32573679", "32573964", "32574058", "32574059", "32574102", "32574205", "32574640", "32574684", "32575561", "32576015", "32576024", "32576033", "32576042", "32576115", "32576392", "32580822", "32588750"]}, "passed_count_currentFile": "27", "isPassedCheck": "False"}, "x6NFJFV7": {"passed_count_linkFile": "0", "itogBoolValue": "False", "trueElems": {}, "passed_count_currentFile": "0", "isPassedCheck": "False"}, "jlDVTDGV": {"passed_count_linkFile": "0", "itogBoolValue": "False", "trueElems": {}, "passed_count_currentFile": "0", "isPassedCheck": "False"}, "TMuCdpIT": {"passed_count_linkFile": "0", "itogBoolValue": "False", "trueElems": {}, "passed_count_currentFile": "0", "isPassedCheck": "False"}, "VOF19a0n": {"passed_count_linkFile": "0", "itogBoolValue": "False", "trueElems": {}, "passed_count_currentFile": "0", "isPassedCheck": "False"}, "QH4Z4CXG": {"passed_count_linkFile": "0", "itogBoolValue": "False", "trueElems": {}, "passed_count_currentFile": "0", "isPassedCheck": "False"}, "aUTWSmI1": {"passed_count_linkFile": "0", "itogBoolValue": "False", "trueElems": {}, "passed_count_currentFile": "0", "isPassedCheck": "False"}, "oBlxSjVD": {"passed_count_linkFile": "0", "itogBoolValue": "False", "trueElems": {}, "passed_count_currentFile": "0", "isPassedCheck": "False"}, "DnHsJdTT": {"passed_count_linkFile": "0", "itogBoolValue": "False", "trueElems": {}, "passed_count_currentFile": "0", "isPassedCheck": "False"}, "lVR3SnUw": {"passed_count_linkFile": "0", "itogBoolValue": "False", "trueElems": {}, "passed_count_currentFile": "0", "isPassedCheck": "False"}, "0zcbc9ub": {"passed_count_linkFile": "0", "itogBoolValue": "False", "trueElems": {}, "passed_count_currentFile": "0", "isPassedCheck": "False"}, "dzGROUdR": {"passed_count_linkFile": "0", "itogBoolValue": "False", "trueElems": {}, "passed_count_currentFile": "0", "isPassedCheck": "False"}, "FDpsTWNY": {"passed_count_linkFile": "0", "itogBoolValue": "False", "trueElems": {}, "passed_count_currentFile": "0", "isPassedCheck": "False"}, "Q6jo8skd": {"passed_count_linkFile": "0", "itogBoolValue": "False", "trueElems": {}, "passed_count_currentFile": "0", "isPassedCheck": "False"}, "pfxNmXBp": {"passed_count_linkFile": "0", "itogBoolValue": "False", "trueElems": {}, "passed_count_currentFile": "0", "isPassedCheck": "False"}, "uh5YNVlv": {"passed_count_linkFile": "0", "itogBoolValue": "False", "trueElems": {}, "passed_count_currentFile": "0", "isPassedCheck": "False"}, "SLRvHOl9": {"passed_count_linkFile": "0", "itogBoolValue": "False", "trueElems": {}, "passed_count_currentFile": "0", "isPassedCheck": "False"}, "E8LOvs5h": {"passed_count_linkFile": "0", "itogBoolValue": "False", "trueElems": {}, "passed_count_currentFile": "0", "isPassedCheck": "False"}, "VolN7KG2": {"passed_count_linkFile": "3", "itogBoolValue": "True", "trueElems": {"05-01-\u041a\u0413-07_\u041a\u0416_\u04213_R24.\u0424\u0425": ["3484951", "3484997", "3503362"]}, "passed_count_currentFile": "0", "isPassedCheck": "False"}, "3qzeXQNK": {"passed_count_linkFile": "1", "itogBoolValue": "True", "trueElems": {"05-01-\u041a\u0413-07_\u041a\u0416_\u04213_R24.\u0424\u0425": ["3483715"]}, "passed_count_currentFile": "0", "isPassedCheck": "False"}, "R979ugxi": {"passed_count_linkFile": "12", "itogBoolValue": "True", "trueElems": {"05-01-\u041a\u0413-07_\u041a\u0416_\u04213_R24.\u0424\u0425": ["3482706", "3483033", "3483053", "3483073", "3483074", "3483135", "3483136", "3483160", "3483161", "3483185", "3483209", "3483219"]}, "passed_count_currentFile": "0", "isPassedCheck": "False"}, "VnccAfvT": {"passed_count_linkFile": "0", "itogBoolValue": "True", "trueElems": {"05-01-\u041a\u0413-07_\u0410\u0420_\u041a\u0420_\u041f\u0430\u0440\u043a\u0438\u043d\u0433+\u04213_R24.\u0424\u0425": ["32634033", "32634445"]}, "passed_count_currentFile": "2", "isPassedCheck": "False"}, "KtEr6zE0": {"passed_count_linkFile": "0", "itogBoolValue": "True", "trueElems": {"05-01-\u041a\u0413-07_\u0410\u0420_\u041a\u0420_\u041f\u0430\u0440\u043a\u0438\u043d\u0433+\u04213_R24.\u0424\u0425": ["32671343", "32671347"]}, "passed_count_currentFile": "2", "isPassedCheck": "False"}, "vwtIdesy": {"passed_count_linkFile": "0", "itogBoolValue": "True", "trueElems": {"05-01-\u041a\u0413-07_\u0410\u0420_\u041a\u0420_\u041f\u0430\u0440\u043a\u0438\u043d\u0433+\u04213_R24.\u0424\u0425": ["32484796"]}, "passed_count_currentFile": "1", "isPassedCheck": "False"}, "v71MGZkD": {"passed_count_linkFile": "1", "itogBoolValue": "True", "trueElems": {"05-01-\u041a\u0413-07_\u041a\u0416_\u04213_R24.\u0424\u0425": ["3521866"]}, "passed_count_currentFile": "0", "isPassedCheck": "False"}, "yhoQpWZQ": {"passed_count_linkFile": "0", "itogBoolValue": "False", "trueElems": {}, "passed_count_currentFile": "0", "isPassedCheck": "False"}, "LAm16y5t": {"passed_count_linkFile": "0", "itogBoolValue": "False", "trueElems": {}, "passed_count_currentFile": "0", "isPassedCheck": "False"}, "r9VOPfOy": {"passed_count_linkFile": "0", "itogBoolValue": "False", "trueElems": {}, "passed_count_currentFile": "0", "isPassedCheck": "False"}, "WBi90VHW": {"passed_count_linkFile": "0", "itogBoolValue": "False", "trueElems": {}, "passed_count_currentFile": "0", "isPassedCheck": "False"}, "BwkQXj1G": {"passed_count_linkFile": "0", "itogBoolValue": "False", "trueElems": {}, "passed_count_currentFile": "0", "isPassedCheck": "False"}, "V44jAz4I": {"passed_count_linkFile": "0", "itogBoolValue": "False", "trueElems": {}, "passed_count_currentFile": "0", "isPassedCheck": "False"}, "Wc76rDa3": {"passed_count_linkFile": "0", "itogBoolValue": "False", "trueElems": {}, "passed_count_currentFile": "0", "isPassedCheck": "False"}, "jhIwp1sl": {"passed_count_linkFile": "0", "itogBoolValue": "False", "trueElems": {}, "passed_count_currentFile": "0", "isPassedCheck": "False"}, "j6LGzf3v": {"passed_count_linkFile": "0", "itogBoolValue": "False", "trueElems": {}, "passed_count_currentFile": "0", "isPassedCheck": "False"}, "RGf4RS1b": {"passed_count_linkFile": "0", "itogBoolValue": "False", "trueElems": {}, "passed_count_currentFile": "0", "isPassedCheck": "False"}, "FxUcyWij": {"passed_count_linkFile": "0", "itogBoolValue": "False", "trueElems": {}, "passed_count_currentFile": "0", "isPassedCheck": "False"}, "Fbb1Ys9C": {"passed_count_linkFile": "0", "itogBoolValue": "False", "trueElems": {}, "passed_count_currentFile": "0", "isPassedCheck": "False"}, "rMMhWJxO": {"passed_count_linkFile": "0", "itogBoolValue": "False", "trueElems": {}, "passed_count_currentFile": "0", "isPassedCheck": "False"}, "yuq2aXf8": {"passed_count_linkFile": "0", "itogBoolValue": "False", "trueElems": {}, "passed_count_currentFile": "0", "isPassedCheck": "False"}, "Xu0BzdGN": {"passed_count_linkFile": "0", "itogBoolValue": "False", "trueElems": {}, "passed_count_currentFile": "0", "isPassedCheck": "False"}, "Q4DlnEID": {"passed_count_linkFile": "0", "itogBoolValue": "False", "trueElems": {}, "passed_count_currentFile": "0", "isPassedCheck": "False"}, "jexZhCp0": {"passed_count_linkFile": "0", "itogBoolValue": "False", "trueElems": {}, "passed_count_currentFile": "0", "isPassedCheck": "False"}, "4L6qRbke": {"passed_count_linkFile": "0", "itogBoolValue": "False", "trueElems": {}, "passed_count_currentFile": "0", "isPassedCheck": "False"}, "WqAVWZt3": {"passed_count_linkFile": "1", "itogBoolValue": "True", "trueElems": {"05-01-\u041a\u0413-07_\u041a\u0416_\u04213_R24.\u0424\u0425": ["3483644"]}, "passed_count_currentFile": "0", "isPassedCheck": "False"}, "2FoZbiKC": {"passed_count_linkFile": "12", "itogBoolValue": "True", "trueElems": {"05-01-\u041a\u0413-07_\u041a\u0416_\u04213_R24.\u0424\u0425": ["3483458", "3483459", "3483460", "3483461", "3483462", "3483463", "3483464", "3483465", "3483466", "3483467", "3483468", "3483469"]}, "passed_count_currentFile": "0", "isPassedCheck": "False"}, "gEupLUIY": {"passed_count_linkFile": "0", "itogBoolValue": "False", "trueElems": {}, "passed_count_currentFile": "0", "isPassedCheck": "False"}, "bfY963my": {"passed_count_linkFile": "0", "itogBoolValue": "False", "trueElems": {}, "passed_count_currentFile": "0", "isPassedCheck": "False"}, "F3QtumvV": {"passed_count_linkFile": "0", "itogBoolValue": "False", "trueElems": {}, "passed_count_currentFile": "0", "isPassedCheck": "False"}, "PW46ygou": {"passed_count_linkFile": "0", "itogBoolValue": "False", "trueElems": {}, "passed_count_currentFile": "0", "isPassedCheck": "False"}, "dQhsc2af": {"passed_count_linkFile": "0", "itogBoolValue": "False", "trueElems": {}, "passed_count_currentFile": "0", "isPassedCheck": "False"}, "VTJfk9JW": {"passed_count_linkFile": "0", "itogBoolValue": "False", "trueElems": {}, "passed_count_currentFile": "0", "isPassedCheck": "False"}, "YwkodMKD": {"passed_count_linkFile": "0", "itogBoolValue": "False", "trueElems": {}, "passed_count_currentFile": "0", "isPassedCheck": "False"}, "PQI8O4oR": {"passed_count_linkFile": "0", "itogBoolValue": "True", "trueElems": {"05-01-\u041a\u0413-07_\u0410\u0420_\u041a\u0420_\u041f\u0430\u0440\u043a\u0438\u043d\u0433+\u04213_R24.\u0424\u0425": ["32632756"]}, "passed_count_currentFile": "1", "isPassedCheck": "False"}, "3Ldw8ZpI": {"passed_count_linkFile": "0", "itogBoolValue": "False", "trueElems": {}, "passed_count_currentFile": "0", "isPassedCheck": "False"}, "0IeZh323": {"passed_count_linkFile": "0", "itogBoolValue": "False", "trueElems": {}, "passed_count_currentFile": "0", "isPassedCheck": "False"}, "xGbhGhOy": {"passed_count_linkFile": "0", "itogBoolValue": "False", "trueElems": {}, "passed_count_currentFile": "0", "isPassedCheck": "False"}, "kMqMPqAi": {"passed_count_linkFile": "0", "itogBoolValue": "False", "trueElems": {}, "passed_count_currentFile": "0", "isPassedCheck": "False"}, "RiiV0ERa": {"passed_count_linkFile": "0", "itogBoolValue": "True", "trueElems": {"05-01-\u041a\u0413-07_\u0410\u0420_\u041a\u0420_\u041f\u0430\u0440\u043a\u0438\u043d\u0433+\u04213_R24.\u0424\u0425": ["32353581", "32353813"]}, "passed_count_currentFile": "2", "isPassedCheck": "False"}, "nvHzxRQl": {"passed_count_linkFile": "0", "itogBoolValue": "False", "trueElems": {}, "passed_count_currentFile": "0", "isPassedCheck": "False"}, "VU7iH5RA": {"passed_count_linkFile": "0", "itogBoolValue": "False", "trueElems": {}, "passed_count_currentFile": "0", "isPassedCheck": "False"}, "ItKGc5bk": {"passed_count_linkFile": "0", "itogBoolValue": "False", "trueElems": {}, "passed_count_currentFile": "0", "isPassedCheck": "False"}, "ZnlWIIVi": {"passed_count_linkFile": "19", "itogBoolValue": "True", "trueElems": {"05-01-\u041a\u0413-07_\u041a\u0416_\u04213_R24.\u0424\u0425": ["3483288", "3483309", "3483575", "3503589", "3503800", "3503870", "3503885", "3503942", "3503950", "3503958", "3503966", "3504082", "3504120", "3504135", "3504152", "3504196", "3504213", "3504228", "3504243"]}, "passed_count_currentFile": "0", "isPassedCheck": "False"}, "E9zlSh3S": {"passed_count_linkFile": "0", "itogBoolValue": "False", "trueElems": {}, "passed_count_currentFile": "0", "isPassedCheck": "False"}, "Gxv7m67S": {"passed_count_linkFile": "0", "itogBoolValue": "False", "trueElems": {}, "passed_count_currentFile": "0", "isPassedCheck": "False"}, "rU1jL9Mx": {"passed_count_linkFile": "0", "itogBoolValue": "False", "trueElems": {}, "passed_count_currentFile": "0", "isPassedCheck": "False"}, "TRLJXQb3": {"passed_count_linkFile": "0", "itogBoolValue": "False", "trueElems": {}, "passed_count_currentFile": "0", "isPassedCheck": "False"}, "Q01pUn7B": {"passed_count_linkFile": "0", "itogBoolValue": "False", "trueElems": {}, "passed_count_currentFile": "0", "isPassedCheck": "False"}, "ltaMdiRT": {"passed_count_linkFile": "0", "itogBoolValue": "False", "trueElems": {}, "passed_count_currentFile": "0", "isPassedCheck": "False"}, "Q8qs9QcO": {"passed_count_linkFile": "0", "itogBoolValue": "False", "trueElems": {}, "passed_count_currentFile": "0", "isPassedCheck": "False"}, "vQSO8Od6": {"passed_count_linkFile": "1", "itogBoolValue": "True", "trueElems": {"05-01-\u041a\u0413-07_\u041a\u0416_\u04213_R24.\u0424\u0425": ["3512413"]}, "passed_count_currentFile": "0", "isPassedCheck": "False"}, "yeIFVhB9": {"passed_count_linkFile": "0", "itogBoolValue": "False", "trueElems": {}, "passed_count_currentFile": "0", "isPassedCheck": "False"}, "4w4OR0pn": {"passed_count_linkFile": "0", "itogBoolValue": "True", "trueElems": {"05-01-\u041a\u0413-07_\u0410\u0420_\u041a\u0420_\u041f\u0430\u0440\u043a\u0438\u043d\u0433+\u04213_R24.\u0424\u0425": ["32398646", "32398647", "32398682"]}, "passed_count_currentFile": "3", "isPassedCheck": "False"}, "AVGlUSiv": {"passed_count_linkFile": "0", "itogBoolValue": "False", "trueElems": {}, "passed_count_currentFile": "0", "isPassedCheck": "False"}, "TG9ls4Gx": {"passed_count_linkFile": "0", "itogBoolValue": "False", "trueElems": {}, "passed_count_currentFile": "0", "isPassedCheck": "False"}, "swm8Ac8c": {"passed_count_linkFile": "0", "itogBoolValue": "False", "trueElems": {}, "passed_count_currentFile": "0", "isPassedCheck": "False"}, "WgwJSiDL": {"passed_count_linkFile": "0", "itogBoolValue": "False", "trueElems": {}, "passed_count_currentFile": "0", "isPassedCheck": "False"}, "wpCjoyrs": {"passed_count_linkFile": "0", "itogBoolValue": "False", "trueElems": {}, "passed_count_currentFile": "0", "isPassedCheck": "False"}, "7NovBnze": {"passed_count_linkFile": "0", "itogBoolValue": "False", "trueElems": {}, "passed_count_currentFile": "0", "isPassedCheck": "False"}, "OavnGEeR": {"passed_count_linkFile": "0", "itogBoolValue": "True", "trueElems": {"05-01-\u041a\u0413-07_\u0410\u0420_\u041a\u0420_\u041f\u0430\u0440\u043a\u0438\u043d\u0433+\u04213_R24.\u0424\u0425": ["32398646", "32398647", "32398682"]}, "passed_count_currentFile": "3", "isPassedCheck": "False"}, "PVyrJGCZ": {"passed_count_linkFile": "0", "itogBoolValue": "False", "trueElems": {}, "passed_count_currentFile": "0", "isPassedCheck": "False"}, "ln6LWMFe": {"passed_count_linkFile": "0", "itogBoolValue": "False", "trueElems": {}, "passed_count_currentFile": "0", "isPassedCheck": "False"}, "wmiVhkgw": {"passed_count_linkFile": "0", "itogBoolValue": "True", "trueElems": {"05-01-\u041a\u0413-07_\u0410\u0420_\u041a\u0420_\u041f\u0430\u0440\u043a\u0438\u043d\u0433+\u04213_R24.\u0424\u0425": ["32673067", "32673109", "32673138", "32673660", "32673661", "32673662"]}, "passed_count_currentFile": "6", "isPassedCheck": "False"}, "EI43nZtM": {"passed_count_linkFile": "0", "itogBoolValue": "False", "trueElems": {}, "passed_count_currentFile": "0", "isPassedCheck": "False"}, "lNQtiAPb": {"passed_count_linkFile": "0", "itogBoolValue": "True", "trueElems": {"05-01-\u041a\u0413-07_\u0410\u0420_\u041a\u0420_\u041f\u0430\u0440\u043a\u0438\u043d\u0433+\u04213_R24.\u0424\u0425": ["32354121", "32354182"]}, "passed_count_currentFile": "2", "isPassedCheck": "False"}, "PVmf570M": {"passed_count_linkFile": "0", "itogBoolValue": "False", "trueElems": {}, "passed_count_currentFile": "0", "isPassedCheck": "False"}, "dgalLchu": {"passed_count_linkFile": "0", "itogBoolValue": "False", "trueElems": {}, "passed_count_currentFile": "0", "isPassedCheck": "False"}, "ptwKFJmh": {"passed_count_linkFile": "0", "itogBoolValue": "False", "trueElems": {}, "passed_count_currentFile": "0", "isPassedCheck": "False"}, "pBp7PDMe": {"passed_count_linkFile": "0", "itogBoolValue": "False", "trueElems": {}, "passed_count_currentFile": "0", "isPassedCheck": "False"}, "WxZhfeFc": {"passed_count_linkFile": "0", "itogBoolValue": "False", "trueElems": {}, "passed_count_currentFile": "0", "isPassedCheck": "False"}, "fpjwUOiB": {"passed_count_linkFile": "0", "itogBoolValue": "False", "trueElems": {}, "passed_count_currentFile": "0", "isPassedCheck": "False"}, "DQa4UF9H": {"passed_count_linkFile": "0", "itogBoolValue": "False", "trueElems": {}, "passed_count_currentFile": "0", "isPassedCheck": "False"}, "T5FmNPyt": {"passed_count_linkFile": "0", "itogBoolValue": "False", "trueElems": {}, "passed_count_currentFile": "0", "isPassedCheck": "False"}, "B2Rq0olh": {"passed_count_linkFile": "0", "itogBoolValue": "False", "trueElems": {}, "passed_count_currentFile": "0", "isPassedCheck": "False"}, "2wRyaUKm": {"passed_count_linkFile": "0", "itogBoolValue": "False", "trueElems": {}, "passed_count_currentFile": "0", "isPassedCheck": "False"}, "qvBFcqVT": {"passed_count_linkFile": "0", "itogBoolValue": "False", "trueElems": {}, "passed_count_currentFile": "0", "isPassedCheck": "False"}, "crWcHsEr": {"passed_count_linkFile": "0", "itogBoolValue": "False", "trueElems": {}, "passed_count_currentFile": "0", "isPassedCheck": "False"}, "TMcfFn6g": {"passed_count_linkFile": "0", "itogBoolValue": "False", "trueElems": {}, "passed_count_currentFile": "0", "isPassedCheck": "False"}, "Us0thtQu": {"passed_count_linkFile": "0", "itogBoolValue": "False", "trueElems": {}, "passed_count_currentFile": "0", "isPassedCheck": "False"}, "mV6bKR0r": {"passed_count_linkFile": "0", "itogBoolValue": "False", "trueElems": {}, "passed_count_currentFile": "0", "isPassedCheck": "False"}, "bhuO39RI": {"passed_count_linkFile": "0", "itogBoolValue": "False", "trueElems": {}, "passed_count_currentFile": "0", "isPassedCheck": "False"}, "Kivcn02u": {"passed_count_linkFile": "0", "itogBoolValue": "False", "trueElems": {}, "passed_count_currentFile": "0", "isPassedCheck": "False"}, "iuEw1W0R": {"passed_count_linkFile": "0", "itogBoolValue": "False", "trueElems": {}, "passed_count_currentFile": "0", "isPassedCheck": "False"}, "JVuCa9YQ": {"passed_count_linkFile": "0", "itogBoolValue": "False", "trueElems": {}, "passed_count_currentFile": "0", "isPassedCheck": "False"}, "mA96P1vf": {"passed_count_linkFile": "0", "itogBoolValue": "False", "trueElems": {}, "passed_count_currentFile": "0", "isPassedCheck": "False"}, "JYufnD6t": {"passed_count_linkFile": "0", "itogBoolValue": "False", "trueElems": {}, "passed_count_currentFile": "0", "isPassedCheck": "False"}, "0oiaW0dj": {"passed_count_linkFile": "0", "itogBoolValue": "False", "trueElems": {}, "passed_count_currentFile": "0", "isPassedCheck": "False"}, "j2Dpw4p6": {"passed_count_linkFile": "0", "itogBoolValue": "False", "trueElems": {}, "passed_count_currentFile": "0", "isPassedCheck": "False"}, "IoM3s6U5": {"passed_count_linkFile": "0", "itogBoolValue": "False", "trueElems": {}, "passed_count_currentFile": "0", "isPassedCheck": "False"}, "j7Z0ww2g": {"passed_count_linkFile": "0", "itogBoolValue": "True", "trueElems": {"05-01-\u041a\u0413-07_\u0410\u0420_\u041a\u0420_\u041f\u0430\u0440\u043a\u0438\u043d\u0433+\u04213_R24.\u0424\u0425": ["32476361", "32482433"]}, "passed_count_currentFile": "2", "isPassedCheck": "False"}, "TtDY6icO": {"passed_count_linkFile": "0", "itogBoolValue": "False", "trueElems": {}, "passed_count_currentFile": "0", "isPassedCheck": "False"}, "U6o5wRL9": {"passed_count_linkFile": "0", "itogBoolValue": "False", "trueElems": {}, "passed_count_currentFile": "0", "isPassedCheck": "False"}, "w89tDpYk": {"passed_count_linkFile": "0", "itogBoolValue": "True", "trueElems": {"05-01-\u041a\u0413-07_\u0410\u0420_\u041a\u0420_\u041f\u0430\u0440\u043a\u0438\u043d\u0433+\u04213_R24.\u0424\u0425": ["32330387", "32330966", "32352350", "32352420", "32352448", "32352476", "32439866", "32439995", "32440026", "32440055"]}, "passed_count_currentFile": "10", "isPassedCheck": "False"}, "oL5cfdw6": {"passed_count_linkFile": "0", "itogBoolValue": "False", "trueElems": {}, "passed_count_currentFile": "0", "isPassedCheck": "False"}, "znnVCMCy": {"passed_count_linkFile": "0", "itogBoolValue": "False", "trueElems": {}, "passed_count_currentFile": "0", "isPassedCheck": "False"}, "2Gdnr0jg": {"passed_count_linkFile": "0", "itogBoolValue": "True", "trueElems": {"05-01-\u041a\u0413-07_\u0410\u0420_\u041a\u0420_\u041f\u0430\u0440\u043a\u0438\u043d\u0433+\u04213_R24.\u0424\u0425": ["32330978", "32352362"]}, "passed_count_currentFile": "2", "isPassedCheck": "False"}, "hHPFt73s": {"passed_count_linkFile": "0", "itogBoolValue": "False", "trueElems": {}, "passed_count_currentFile": "0", "isPassedCheck": "False"}, "7kKTTcnb": {"passed_count_linkFile": "0", "itogBoolValue": "True", "trueElems": {"05-01-\u041a\u0413-07_\u0410\u0420_\u041a\u0420_\u041f\u0430\u0440\u043a\u0438\u043d\u0433+\u04213_R24.\u0424\u0425": ["32639015", "32639197"]}, "passed_count_currentFile": "2", "isPassedCheck": "False"}, "Hqiw9xKn": {"passed_count_linkFile": "0", "itogBoolValue": "False", "trueElems": {}, "passed_count_currentFile": "0", "isPassedCheck": "False"}, "nZ89BUq8": {"passed_count_linkFile": "0", "itogBoolValue": "False", "trueElems": {}, "passed_count_currentFile": "0", "isPassedCheck": "False"}, "ZGc8VZNP": {"passed_count_linkFile": "0", "itogBoolValue": "False", "trueElems": {}, "passed_count_currentFile": "0", "isPassedCheck": "False"}, "amRfyHUJ": {"passed_count_linkFile": "0", "itogBoolValue": "True", "trueElems": {"05-01-\u041a\u0413-07_\u0410\u0420_\u041a\u0420_\u041f\u0430\u0440\u043a\u0438\u043d\u0433+\u04213_R24.\u0424\u0425": ["32400223"]}, "passed_count_currentFile": "1", "isPassedCheck": "False"}, "62tVu03w": {"passed_count_linkFile": "0", "itogBoolValue": "False", "trueElems": {}, "passed_count_currentFile": "0", "isPassedCheck": "False"}, "6YjgbPzb": {"passed_count_linkFile": "0", "itogBoolValue": "False", "trueElems": {}, "passed_count_currentFile": "0", "isPassedCheck": "False"}, "WcLlfSIn": {"passed_count_linkFile": "0", "itogBoolValue": "False", "trueElems": {}, "passed_count_currentFile": "0", "isPassedCheck": "False"}, "h3xEwDm4": {"passed_count_linkFile": "0", "itogBoolValue": "True", "trueElems": {"05-01-\u041a\u0413-07_\u0410\u0420_\u041a\u0420_\u041f\u0430\u0440\u043a\u0438\u043d\u0433+\u04213_R24.\u0424\u0425": ["32437715", "32438384", "32438853"]}, "passed_count_currentFile": "3", "isPassedCheck": "False"}, "rzeXLRiq": {"passed_count_linkFile": "0", "itogBoolValue": "False", "trueElems": {}, "passed_count_currentFile": "0", "isPassedCheck": "False"}, "bHyFO76l": {"passed_count_linkFile": "0", "itogBoolValue": "False", "trueElems": {}, "passed_count_currentFile": "0", "isPassedCheck": "False"}, "SajWamxY": {"passed_count_linkFile": "0", "itogBoolValue": "True", "trueElems": {"05-01-\u041a\u0413-07_\u0410\u0420_\u041a\u0420_\u041f\u0430\u0440\u043a\u0438\u043d\u0433+\u04213_R24.\u0424\u0425": ["32511684", "32512359", "32512407"]}, "passed_count_currentFile": "3", "isPassedCheck": "False"}, "GaUyWO9b": {"passed_count_linkFile": "0", "itogBoolValue": "False", "trueElems": {}, "passed_count_currentFile": "0", "isPassedCheck": "False"}, "xDq6k8ni": {"passed_count_linkFile": "0", "itogBoolValue": "True", "trueElems": {"05-01-\u041a\u0413-07_\u0410\u0420_\u041a\u0420_\u041f\u0430\u0440\u043a\u0438\u043d\u0433+\u04213_R24.\u0424\u0425": ["32352711", "32425156", "32425353", "32425746", "32426824", "32427713", "32427940", "32428110", "32428467", "32428547", "32428841", "32428906", "32429243", "32430009", "32430019", "32430027", "32430035", "32430043", "32430561", "32648923"]}, "passed_count_currentFile": "20", "isPassedCheck": "False"}, "2v2paGsx": {"passed_count_linkFile": "0", "itogBoolValue": "True", "trueElems": {"05-01-\u041a\u0413-07_\u0410\u0420_\u041a\u0420_\u041f\u0430\u0440\u043a\u0438\u043d\u0433+\u04213_R24.\u0424\u0425": ["32352711", "32425156", "32425353", "32425746", "32426824", "32427713", "32427940", "32428110", "32428467", "32428547", "32428841", "32428906", "32429243", "32430009", "32430019", "32430027", "32430035", "32430043", "32430561", "32648923"]}, "passed_count_currentFile": "20", "isPassedCheck": "False"}, "9qTlppd2": {"passed_count_linkFile": "0", "itogBoolValue": "False", "trueElems": {}, "passed_count_currentFile": "0", "isPassedCheck": "False"}, "RjLY2W9u": {"passed_count_linkFile": "0", "itogBoolValue": "False", "trueElems": {}, "passed_count_currentFile": "0", "isPassedCheck": "False"}, "8OyHzcUr": {"passed_count_linkFile": "0", "itogBoolValue": "True", "trueElems": {"05-01-\u041a\u0413-07_\u0410\u0420_\u041a\u0420_\u041f\u0430\u0440\u043a\u0438\u043d\u0433+\u04213_R24.\u0424\u0425": ["32353458", "32399882", "32402035"]}, "passed_count_currentFile": "3", "isPassedCheck": "False"}, "VVuBubeM": {"passed_count_linkFile": "0", "itogBoolValue": "False", "trueElems": {}, "passed_count_currentFile": "0", "isPassedCheck": "False"}, "KXRzyc9Q": {"passed_count_linkFile": "0", "itogBoolValue": "False", "trueElems": {}, "passed_count_currentFile": "0", "isPassedCheck": "False"}, "d63Pnwua": {"passed_count_linkFile": "0", "itogBoolValue": "False", "trueElems": {}, "passed_count_currentFile": "0", "isPassedCheck": "False"}, "ILpUToEs": {"passed_count_linkFile": "0", "itogBoolValue": "False", "trueElems": {}, "passed_count_currentFile": "0", "isPassedCheck": "False"}, "Jcli1yvb": {"passed_count_linkFile": "0", "itogBoolValue": "False", "trueElems": {}, "passed_count_currentFile": "0", "isPassedCheck": "False"}, "3OB920R7": {"passed_count_linkFile": "0", "itogBoolValue": "False", "trueElems": {}, "passed_count_currentFile": "0", "isPassedCheck": "False"}, "R2O7z0oM": {"passed_count_linkFile": "0", "itogBoolValue": "True", "trueElems": {"05-01-\u041a\u0413-07_\u0410\u0420_\u041a\u0420_\u041f\u0430\u0440\u043a\u0438\u043d\u0433+\u04213_R24.\u0424\u0425": ["32577559", "32577599", "32577639", "32577690", "32577868", "32578184", "32578382", "32578835", "32578861", "32578942", "32578968", "32579235", "32579459", "32588867"]}, "passed_count_currentFile": "14", "isPassedCheck": "False"}, "TSMugzx1": {"passed_count_linkFile": "0", "itogBoolValue": "False", "trueElems": {}, "passed_count_currentFile": "0", "isPassedCheck": "False"}, "tGpfuUiN": {"passed_count_linkFile": "0", "itogBoolValue": "False", "trueElems": {}, "passed_count_currentFile": "0", "isPassedCheck": "False"}, "Bz4Dboje": {"passed_count_linkFile": "0", "itogBoolValue": "True", "trueElems": {"05-01-\u041a\u0413-07_\u0410\u0420_\u041a\u0420_\u041f\u0430\u0440\u043a\u0438\u043d\u0433+\u04213_R24.\u0424\u0425": ["32548709", "32579606", "32579971", "32580095", "32580282", "32665783"]}, "passed_count_currentFile": "6", "isPassedCheck": "False"}, "DkBsGLJ7": {"passed_count_linkFile": "0", "itogBoolValue": "False", "trueElems": {}, "passed_count_currentFile": "0", "isPassedCheck": "False"}, "4gx468ZO": {"passed_count_linkFile": "0", "itogBoolValue": "False", "trueElems": {}, "passed_count_currentFile": "0", "isPassedCheck": "False"}, "xyz48bro": {"passed_count_linkFile": "0", "itogBoolValue": "False", "trueElems": {}, "passed_count_currentFile": "0", "isPassedCheck": "False"}, "5YZemVOp": {"passed_count_linkFile": "0", "itogBoolValue": "False", "trueElems": {}, "passed_count_currentFile": "0", "isPassedCheck": "False"}, "s5LZr0IT": {"passed_count_linkFile": "0", "itogBoolValue": "False", "trueElems": {}, "passed_count_currentFile": "0", "isPassedCheck": "False"}, "oLPi7ZtY": {"passed_count_linkFile": "0", "itogBoolValue": "True", "trueElems": {"05-01-\u041a\u0413-07_\u0410\u0420_\u041a\u0420_\u041f\u0430\u0440\u043a\u0438\u043d\u0433+\u04213_R24.\u0424\u0425": ["32398011", "32398070"]}, "passed_count_currentFile": "2", "isPassedCheck": "False"}, "IhMeEIpV": {"passed_count_linkFile": "0", "itogBoolValue": "True", "trueElems": {"05-01-\u041a\u0413-07_\u0410\u0420_\u041a\u0420_\u041f\u0430\u0440\u043a\u0438\u043d\u0433+\u04213_R24.\u0424\u0425": ["32563318", "32563434", "32563714", "32563715", "32563716", "32563717", "32563947", "32564268", "32564410", "32564411", "32564640", "32564931", "32565169", "32565300", "32685434", "32685478", "32685533", "32685565", "32685740", "32685773", "32685795", "32685817", "32685922", "32685941", "32685959", "32685983", "32686130", "32686156", "32686182", "32686209", "32686315", "32686499", "32686520", "32686550", "32686828", "32686947", "32686978", "32687018", "32687083", "32687084", "32687085", "32687101", "32687102", "32687103", "32687118", "32687119", "32687120", "32687121", "32687164", "32687190", "32687220", "32687298", "32687330", "32687355", "32687424", "32687455", "32687484"]}, "passed_count_currentFile": "57", "isPassedCheck": "False"}, "Akq0rRzG": {"passed_count_linkFile": "0", "itogBoolValue": "True", "trueElems": {"05-01-\u041a\u0413-07_\u0410\u0420_\u041a\u0420_\u041f\u0430\u0440\u043a\u0438\u043d\u0433+\u04213_R24.\u0424\u0425": ["32327012", "32329284", "32329406", "32329521", "32329594", "32329716", "32329872"]}, "passed_count_currentFile": "7", "isPassedCheck": "False"}, "ap12tohf": {"passed_count_linkFile": "0", "itogBoolValue": "False", "trueElems": {}, "passed_count_currentFile": "0", "isPassedCheck": "False"}, "F0zzCty7": {"passed_count_linkFile": "0", "itogBoolValue": "False", "trueElems": {}, "passed_count_currentFile": "0", "isPassedCheck": "False"}, "uqsS0UbW": {"passed_count_linkFile": "0", "itogBoolValue": "False", "trueElems": {}, "passed_count_currentFile": "0", "isPassedCheck": "False"}, "ZuwRAjbR": {"passed_count_linkFile": "0", "itogBoolValue": "False", "trueElems": {}, "passed_count_currentFile": "0", "isPassedCheck": "False"}}